basicMLpy/__init__.py
basicMLpy/classification.py
basicMLpy/decomposition.py
basicMLpy/ensemble.py
basicMLpy/loss_functions.py
basicMLpy/model_selection.py
basicMLpy/nearest_neighbors.py
basicMLpy/regression.py
basicMLpy/utils.py
basicMLpy-1.0.9.1.dist-info/LICENSE.txt
basicMLpy-1.0.9.1.dist-info/METADATA
basicMLpy-1.0.9.1.dist-info/WHEEL
basicMLpy-1.0.9.1.dist-info/top_level.txt
basicMLpy-1.0.9.1.dist-info/RECORD
