Metadata-Version: 2.1
Name: basicMLpy
Version: 1.0.9.1
Summary: A collection of simple machine learning algorithms
Home-page: https://github.com/HenrySilvaCS/basicMLpy
Author: Henrique Soares Assumpção e Silva
Author-email: henriquesoares@dcc.ufmg.br
License: UNKNOWN
Platform: UNKNOWN
Classifier: Programming Language :: Python :: 3
Classifier: License :: OSI Approved :: MIT License
Classifier: Operating System :: OS Independent
Requires-Python: >=3.8
License-File: LICENSE.txt
Requires-Dist: numpy (>=1.19)
Requires-Dist: scipy (>=1.5.2)
Requires-Dist: scikit-learn (>=0.23)
